README.md
setup.py
django_po_translator/__init__.py
django_po_translator/app_settings.py
django_po_translator/apps.py
django_po_translator/helpers.py
django_po_translator/po_processor.py
django_po_translator/tests.py
django_po_translator/translate.py
django_po_translator.egg-info/PKG-INFO
django_po_translator.egg-info/SOURCES.txt
django_po_translator.egg-info/dependency_links.txt
django_po_translator.egg-info/requires.txt
django_po_translator.egg-info/top_level.txt
django_po_translator/management/__init__.py
django_po_translator/management/commands/__init__.py
django_po_translator/management/commands/translate.py
django_po_translator/management/commands/__pycache__/__init__.cpython-39.pyc
django_po_translator/management/commands/__pycache__/restore_po_formatting.cpython-39.pyc
django_po_translator/management/commands/__pycache__/translate.cpython-39.pyc
django_po_translator/test_files/test_po.po