Metadata-Version: 2.1
Name: django-po-translator
Version: 1.0.0
Summary: Translate Django PO files and resolve fuzziness with ease.
Home-page: https://github.com/waseem-hamoolaila/django-po-translator
Author: Waseem Hamoolaila
Author-email: waseem.97.laila@gmail.com
Classifier: Development Status :: 3 - Alpha
Classifier: Intended Audience :: Developers
Classifier: License :: OSI Approved :: MIT License
